dppvalidator/__init__.py
dppvalidator/logging.py
dppvalidator/py.typed
dppvalidator/cli/__init__.py
dppvalidator/cli/console.py
dppvalidator/cli/main.py
dppvalidator/cli/commands/__init__.py
dppvalidator/cli/commands/completions.py
dppvalidator/cli/commands/doctor.py
dppvalidator/cli/commands/export.py
dppvalidator/cli/commands/init.py
dppvalidator/cli/commands/precommit.py
dppvalidator/cli/commands/schema.py
dppvalidator/cli/commands/validate.py
dppvalidator/cli/commands/watch.py
dppvalidator/exporters/__init__.py
dppvalidator/exporters/contexts.py
dppvalidator/exporters/json.py
dppvalidator/exporters/jsonld.py
dppvalidator/exporters/protocols.py
dppvalidator/models/__init__.py
dppvalidator/models/base.py
dppvalidator/models/claims.py
dppvalidator/models/credential.py
dppvalidator/models/enums.py
dppvalidator/models/identifiers.py
dppvalidator/models/materials.py
dppvalidator/models/passport.py
dppvalidator/models/performance.py
dppvalidator/models/primitives.py
dppvalidator/models/product.py
dppvalidator/models/protocols.py
dppvalidator/plugins/__init__.py
dppvalidator/plugins/discovery.py
dppvalidator/plugins/registry.py
dppvalidator/schemas/__init__.py
dppvalidator/schemas/loader.py
dppvalidator/schemas/registry.py
dppvalidator/schemas/data/README.md
dppvalidator/schemas/data/untp-dpp-schema-0.6.1.json
dppvalidator/validators/__init__.py
dppvalidator/validators/deep.py
dppvalidator/validators/detection.py
dppvalidator/validators/engine.py
dppvalidator/validators/errors.py
dppvalidator/validators/jsonld_semantic.py
dppvalidator/validators/layers.py
dppvalidator/validators/model.py
dppvalidator/validators/protocols.py
dppvalidator/validators/results.py
dppvalidator/validators/schema.py
dppvalidator/validators/semantic.py
dppvalidator/validators/rules/__init__.py
dppvalidator/validators/rules/base.py
dppvalidator/verifier/__init__.py
dppvalidator/verifier/did.py
dppvalidator/verifier/signatures.py
dppvalidator/verifier/verifier.py
dppvalidator-0.2.4.dist-info/METADATA
dppvalidator-0.2.4.dist-info/WHEEL
dppvalidator-0.2.4.dist-info/entry_points.txt
dppvalidator-0.2.4.dist-info/licenses/LICENSE
dppvalidator-0.2.4.dist-info/RECORD
