Metadata-Version: 2.4
Name: dppvalidator
Version: 0.2.4
Summary: Python library for validating Digital Product Passports (DPP) according to EU ESPR regulations and CIRPASS/UNECE ontologies
Project-URL: Homepage, https://github.com/artiso-ai/dppvalidator
Project-URL: Repository, https://github.com/artiso-ai/dppvalidator
Project-URL: Documentation, https://artiso-ai.github.io/dppvalidator/
Project-URL: Changelog, https://github.com/artiso-ai/dppvalidator/blob/main/CHANGELOG.md
Project-URL: Issues, https://github.com/artiso-ai/dppvalidator/issues
Author: artiso-ai
License: MIT
License-File: LICENSE
Keywords: cirpass,digital-product-passport,dpp,espr,pydantic,validation
Classifier: Development Status :: 4 - Beta
Classifier: Framework :: Pydantic :: 2
Classifier: Intended Audience :: Developers
Classifier: Intended Audience :: Manufacturing
Classifier: License :: OSI Approved :: MIT License
Classifier: Operating System :: OS Independent
Classifier: Programming Language :: Python :: 3
Classifier: Programming Language :: Python :: 3.10
Classifier: Programming Language :: Python :: 3.11
Classifier: Programming Language :: Python :: 3.12
Classifier: Programming Language :: Python :: 3.13
Classifier: Programming Language :: Python :: 3.14
Classifier: Topic :: Scientific/Engineering :: Information Analysis
Classifier: Topic :: Software Development :: Libraries :: Python Modules
Classifier: Topic :: Software Development :: Quality Assurance
Classifier: Typing :: Typed
Requires-Python: >=3.10
Requires-Dist: cryptography>=43.0.0
Requires-Dist: httpx>=0.28.0
Requires-Dist: jsonschema>=4.23.0
Requires-Dist: pydantic>=2.12.5
Requires-Dist: pyjwt>=2.9.0
Requires-Dist: pyld>=2.0.4
Provides-Extra: cli
Requires-Dist: rich>=13.0.0; extra == 'cli'
